[
  {
    "text": "Comprehensive Guide to Major Cities in the South of France",
    "features": {
      "source": "OCR",
      "page": 1
    }
  },
  {
    "text": "Introduction",
    "features": {
      "source": "OCR",
      "page": 1
    }
  },
  {
    "text": "The South of France, known for its stunning landscapes, Mediterranean coastline, and rich",
    "features": {
      "source": "OCR",
      "page": 1
    }
  },
  {
    "text": "cultural heritage, is home to some of the most beautiful and historically significant cities in the",
    "features": {
      "source": "OCR",
      "page": 1
    }
  },
  {
    "text": "country. This guide provides an in-depth look at the major cities in the South of France,",
    "features": {
      "source": "OCR",
      "page": 1
    }
  },
  {
    "text": "detailing their history, key attractions, cultural highlights, and unique characteristics. Whether",
    "features": {
      "source": "OCR",
      "page": 1
    }
  },
  {
    "text": "you're planning a visit or simply want to learn more about this enchanting region, this guide",
    "features": {
      "source": "OCR",
      "page": 1
    }
  },
  {
    "text": "will offer valuable insights into each city's charm and allure.",
    "features": {
      "source": "OCR",
      "page": 1
    }
  },
  {
    "text": "Overview of the Region",
    "features": {
      "source": "OCR",
      "page": 2
    }
  },
  {
    "text": "The South of France, or \"Le Midi,\u2019 encompasses the regions of Provence-Alpes-C\u00e9te d'Azur,",
    "features": {
      "source": "OCR",
      "page": 2
    }
  },
  {
    "text": "Occitanie, and parts of Nouvelle-Aquitaine. This area is renowned for its diverse landscapes,",
    "features": {
      "source": "OCR",
      "page": 2
    }
  },
  {
    "text": "from the sun-drenched beaches of the French Riviera to the rolling vineyards of Provence and",
    "features": {
      "source": "OCR",
      "page": 2
    }
  },
  {
    "text": "the rugged Pyrenees mountains. The Mediterranean climate ensures warm summers and",
    "features": {
      "source": "OCR",
      "page": 2
    }
  },
  {
    "text": "mild winters, making it a year-round destination. The South of France is also famous for its",
    "features": {
      "source": "OCR",
      "page": 2
    }
  },
  {
    "text": "cuisine, wines, and vibrant cultural scene.",
    "features": {
      "source": "OCR",
      "page": 2
    }
  },
  {
    "text": "Travel Tips",
    "features": {
      "source": "OCR",
      "page": 2
    }
  },
  {
    "text": "\u00ab Best Time to Visit: The best time to visit the South of France is during the spring (April",
    "features": {
      "source": "OCR",
      "page": 2
    }
  },
  {
    "text": "to June) and fall (September to October) when the weather is pleasant, and the tourist",
    "features": {
      "source": "OCR",
      "page": 2
    }
  },
  {
    "text": "crowds are smaller.",
    "features": {
      "source": "OCR",
      "page": 2
    }
  },
  {
    "text": "\u00a2 Transportation: The region is well-connected by an extensive network of trains,",
    "features": {
      "source": "OCR",
      "page": 2
    }
  },
  {
    "text": "buses, and flights. Renting a car is also a great option for exploring the countryside",
    "features": {
      "source": "OCR",
      "page": 2
    }
  },
  {
    "text": "and smaller towns.",
    "features": {
      "source": "OCR",
      "page": 2
    }
  },
  {
    "text": "\u00a2 Language: While French is the official language, English is widely spoken in tourist",
    "features": {
      "source": "OCR",
      "page": 2
    }
  },
  {
    "text": "areas. Learning a few basic French phrases can enhance your travel experience.",
    "features": {
      "source": "OCR",
      "page": 2
    }
  },
  {
    "text": "Marseille: The Oldest City in France",
    "features": {
      "source": "OCR",
      "page": 3
    }
  },
  {
    "text": "History",
    "features": {
      "source": "OCR",
      "page": 3
    }
  },
  {
    "text": "Marseille, founded by Greek sailors around 600 BC, is the oldest city in France. Its strategic",
    "features": {
      "source": "OCR",
      "page": 3
    }
  },
  {
    "text": "location on the Mediterranean coast made it a vital trading port throughout history. The city's",
    "features": {
      "source": "OCR",
      "page": 3
    }
  },
  {
    "text": "rich cultural heritage is reflected in its diverse architecture and vibrant atmosphere. Over the",
    "features": {
      "source": "OCR",
      "page": 3
    }
  },
  {
    "text": "centuries, Marseille has been influenced by various cultures, including Greek, Roman, and",
    "features": {
      "source": "OCR",
      "page": 3
    }
  },
  {
    "text": "North African, making it a melting pot of traditions and customs.",
    "features": {
      "source": "OCR",
      "page": 3
    }
  },
  {
    "text": "Key Attractions",
    "features": {
      "source": "OCR",
      "page": 3
    }
  },
  {
    "text": "Old Port (Vieux-Port): The heart of Marseille, the Old Port has been a bustling harbor",
    "features": {
      "source": "OCR",
      "page": 3
    }
  },
  {
    "text": "for over 2,600 years. Today, it is a lively area filled with cafes, restaurants, and",
    "features": {
      "source": "OCR",
      "page": 3
    }
  },
  {
    "text": "markets.",
    "features": {
      "source": "OCR",
      "page": 3
    }
  },
  {
    "text": "Basilica of Notre-Dame de la Garde: This iconic basilica, perched on a hill",
    "features": {
      "source": "OCR",
      "page": 3
    }
  },
  {
    "text": "overlooking the city, offers panoramic views of Marseille and the Mediterranean Sea.",
    "features": {
      "source": "OCR",
      "page": 3
    }
  },
  {
    "text": "Built in the 19th century, it is a symbol of the city's maritime heritage.",
    "features": {
      "source": "OCR",
      "page": 3
    }
  },
  {
    "text": "MuCEM (Museum of European and Mediterranean Civilizations): This modern",
    "features": {
      "source": "OCR",
      "page": 3
    }
  },
  {
    "text": "museum explores the cultural history of the Mediterranean region through a variety of",
    "features": {
      "source": "OCR",
      "page": 3
    }
  },
  {
    "text": "exhibits and interactive displays.",
    "features": {
      "source": "OCR",
      "page": 3
    }
  },
  {
    "text": "Le Panier: The oldest district in Marseille, Le Panier is a maze of narrow streets,",
    "features": {
      "source": "OCR",
      "page": 3
    }
  },
  {
    "text": "colorful buildings, and historic landmarks. It's a great place to explore the city's past",
    "features": {
      "source": "OCR",
      "page": 3
    }
  },
  {
    "text": "and enjoy its vibrant culture.",
    "features": {
      "source": "OCR",
      "page": 3
    }
  },
  {
    "text": "Local Experiences",
    "features": {
      "source": "OCR",
      "page": 3
    }
  },
  {
    "text": "Boat Trip to the Calanques: Take a boat trip to the Calanques, a series of stunning",
    "features": {
      "source": "OCR",
      "page": 3
    }
  },
  {
    "text": "limestone cliffs and coves along the coast.",
    "features": {
      "source": "OCR",
      "page": 3
    }
  },
  {
    "text": "Fish Market at the Old Port: Visit the fish market at the Old Port to experience the",
    "features": {
      "source": "OCR",
      "page": 3
    }
  },
  {
    "text": "local seafood culture.",
    "features": {
      "source": "OCR",
      "page": 3
    }
  },
  {
    "text": "Street Art in Cours Julien: Explore the vibrant street art scene in the Cours Julien",
    "features": {
      "source": "OCR",
      "page": 3
    }
  },
  {
    "text": "district.",
    "features": {
      "source": "OCR",
      "page": 3
    }
  },
  {
    "text": "Cultural Highlights",
    "features": {
      "source": "OCR",
      "page": 3
    }
  },
  {
    "text": "Marseille is known for its vibrant arts scene, with numerous galleries, theaters, and music",
    "features": {
      "source": "OCR",
      "page": 3
    }
  },
  {
    "text": "venues. The city hosts several festivals throughout the year, including the Festival de",
    "features": {
      "source": "OCR",
      "page": 3
    }
  },
  {
    "text": "Marseille, which celebrates contemporary dance, theater, and music. Marseille's cuisine is",
    "features": {
      "source": "OCR",
      "page": 3
    }
  },
  {
    "text": "also a highlight, with dishes like bouillabaisse (a traditional fish stew) and pastis (an anise-",
    "features": {
      "source": "OCR",
      "page": 4
    }
  },
  {
    "text": "flavored aperitif) being local favorites.",
    "features": {
      "source": "OCR",
      "page": 4
    }
  },
  {
    "text": "Nice: The Jewel of the French Riviera",
    "features": {
      "source": "OCR",
      "page": 5
    }
  },
  {
    "text": "History",
    "features": {
      "source": "OCR",
      "page": 5
    }
  },
  {
    "text": "Nice, located on the French Riviera, has been a popular destination for centuries. Its history",
    "features": {
      "source": "OCR",
      "page": 5
    }
  },
  {
    "text": "dates back to the ancient Greeks, who founded the city around 350 BC. Nice later became a",
    "features": {
      "source": "OCR",
      "page": 5
    }
  },
  {
    "text": "Roman colony and has since evolved into a glamorous resort town. In the 19th century, Nice",
    "features": {
      "source": "OCR",
      "page": 5
    }
  },
  {
    "text": "became a favorite winter retreat for European aristocrats, which contributed to its",
    "features": {
      "source": "OCR",
      "page": 5
    }
  },
  {
    "text": "development as a luxurious destination.",
    "features": {
      "source": "OCR",
      "page": 5
    }
  },
  {
    "text": "Key Attractions",
    "features": {
      "source": "OCR",
      "page": 5
    }
  },
  {
    "text": "Promenade des Anglais: This famous seaside promenade, built in the 19th century, is",
    "features": {
      "source": "OCR",
      "page": 5
    }
  },
  {
    "text": "perfect for a leisurely stroll along the coast. It offers stunning views of the",
    "features": {
      "source": "OCR",
      "page": 5
    }
  },
  {
    "text": "Mediterranean and is lined with cafes and hotels.",
    "features": {
      "source": "OCR",
      "page": 5
    }
  },
  {
    "text": "Castle Hill (Colline du Chateau): This hilltop park offers panoramic views of Nice and",
    "features": {
      "source": "OCR",
      "page": 5
    }
  },
  {
    "text": "the Mediterranean. It was once the site of a medieval castle, which was destroyed in",
    "features": {
      "source": "OCR",
      "page": 5
    }
  },
  {
    "text": "the 18th century.",
    "features": {
      "source": "OCR",
      "page": 5
    }
  },
  {
    "text": "Old Town (Vieux Nice): The historic center of Nice is a labyrinth of narrow streets,",
    "features": {
      "source": "OCR",
      "page": 5
    }
  },
  {
    "text": "baroque churches, and bustling markets. Don't miss the Cours Saleya market, where",
    "features": {
      "source": "OCR",
      "page": 5
    }
  },
  {
    "text": "you can find fresh produce, flowers, and local delicacies.",
    "features": {
      "source": "OCR",
      "page": 5
    }
  },
  {
    "text": "Matisse Museum: Dedicated to the warks of Henri Matisse, who spent much of his life",
    "features": {
      "source": "OCR",
      "page": 5
    }
  },
  {
    "text": "in Nice, this museum features a comprehensive callection of his paintings, sculptures,",
    "features": {
      "source": "OCR",
      "page": 5
    }
  },
  {
    "text": "and drawings.",
    "features": {
      "source": "OCR",
      "page": 5
    }
  },
  {
    "text": "Hidden Gems",
    "features": {
      "source": "OCR",
      "page": 5
    }
  },
  {
    "text": "Russian Orthodox Cathedral: Visit the stunning Russian Orthodox Cathedral, a",
    "features": {
      "source": "OCR",
      "page": 5
    }
  },
  {
    "text": "unique architectural gem in Nice.",
    "features": {
      "source": "OCR",
      "page": 5
    }
  },
  {
    "text": "Marc Chagall National Museum: Explore the works of Marc Chagall at this dedicated",
    "features": {
      "source": "OCR",
      "page": 5
    }
  },
  {
    "text": "museum.",
    "features": {
      "source": "OCR",
      "page": 5
    }
  },
  {
    "text": "Pare Phoenix: Discover the botanical wonders at Parc Phoenix, a beautiful garden and",
    "features": {
      "source": "OCR",
      "page": 5
    }
  },
  {
    "text": "park.",
    "features": {
      "source": "OCR",
      "page": 5
    }
  },
  {
    "text": "Cultural Highlights",
    "features": {
      "source": "OCR",
      "page": 5
    }
  },
  {
    "text": "Nice is renowned for its vibrant cultural scene, with numerous museums, galleries, and",
    "features": {
      "source": "OCR",
      "page": 5
    }
  },
  {
    "text": "theaters. The city hosts the Nice Carnival in February, one of the largest and oldest carnivals",
    "features": {
      "source": "OCR",
      "page": 5
    }
  },
  {
    "text": "in the world. The Nice Jazz Festival, held in July, is another major event that attracts music",
    "features": {
      "source": "OCR",
      "page": 5
    }
  },
  {
    "text": "lovers from around the globe. Nice's cuisine is also a highlight, with dishes like salade nicoise",
    "features": {
      "source": "OCR",
      "page": 6
    }
  },
  {
    "text": "and socca (a chickpea flour pancake) being local specialties.",
    "features": {
      "source": "OCR",
      "page": 6
    }
  },
  {
    "text": "Avignon: The City of Popes",
    "features": {
      "source": "OCR",
      "page": 7
    }
  },
  {
    "text": "History",
    "features": {
      "source": "OCR",
      "page": 7
    }
  },
  {
    "text": "Avignon, located on the banks of the Rh\u00e9ne River, is best known for its role as the seat of the",
    "features": {
      "source": "OCR",
      "page": 7
    }
  },
  {
    "text": "papacy in the 14th century. The city was home to seven popes during this period, leaving a",
    "features": {
      "source": "OCR",
      "page": 7
    }
  },
  {
    "text": "lasting legacy of impressive architecture and cultural heritage. Avignon's history dates back to",
    "features": {
      "source": "OCR",
      "page": 7
    }
  },
  {
    "text": "Roman times, and it has been a significant religious and cultural center for centuries.",
    "features": {
      "source": "OCR",
      "page": 7
    }
  },
  {
    "text": "Key Attractions",
    "features": {
      "source": "OCR",
      "page": 7
    }
  },
  {
    "text": "\u00ab Palais des Papes: This massive Gothic palace was the residence of the popes during",
    "features": {
      "source": "OCR",
      "page": 7
    }
  },
  {
    "text": "their stay in Avignon. It is one of the largest and most important medieval Gothic",
    "features": {
      "source": "OCR",
      "page": 7
    }
  },
  {
    "text": "buildings in Europe.",
    "features": {
      "source": "OCR",
      "page": 7
    }
  },
  {
    "text": "+ Pont Saint-B\u00e9n\u00e9zet (Pont d'Avignon): This famous bridge, immortalized in the song",
    "features": {
      "source": "OCR",
      "page": 7
    }
  },
  {
    "text": "\u201cSur le Pont d'Avignon,\" was built in the 12th century. Although only a few arches",
    "features": {
      "source": "OCR",
      "page": 7
    }
  },
  {
    "text": "remain, it is a UNESCO World Heritage site.",
    "features": {
      "source": "OCR",
      "page": 7
    }
  },
  {
    "text": "\u00ab Avignon Cathedral: Located next to the Palais des Papes, this Romanesque cathedral",
    "features": {
      "source": "OCR",
      "page": 7
    }
  },
  {
    "text": "dates back to the 12th century and features a gilded statue of the Virgin Mary.",
    "features": {
      "source": "OCR",
      "page": 7
    }
  },
  {
    "text": "* Place de l'Horloge: The main square in Avignon, this lively area is surrounded by",
    "features": {
      "source": "OCR",
      "page": 7
    }
  },
  {
    "text": "cafes, restaurants, and historic buildings, including the 19th-century town hall and",
    "features": {
      "source": "OCR",
      "page": 7
    }
  },
  {
    "text": "opera house.",
    "features": {
      "source": "OCR",
      "page": 7
    }
  },
  {
    "text": "Cultural Activities",
    "features": {
      "source": "OCR",
      "page": 7
    }
  },
  {
    "text": "e Op\u00e9ra Grand Avignon: Attend a performance at the Op\u00e9ra Grand Avignon for a",
    "features": {
      "source": "OCR",
      "page": 7
    }
  },
  {
    "text": "cultural treat.",
    "features": {
      "source": "OCR",
      "page": 7
    }
  },
  {
    "text": "\u00ab Arts Scene: Explore the city's vibrant arts scene, with numerous galleries and",
    "features": {
      "source": "OCR",
      "page": 7
    }
  },
  {
    "text": "exhibitions.",
    "features": {
      "source": "OCR",
      "page": 7
    }
  },
  {
    "text": "Cultural Highlights",
    "features": {
      "source": "OCR",
      "page": 7
    }
  },
  {
    "text": "Avignon is famous for its annual Festival d\u2018Avignon, held in July, which is one of the most",
    "features": {
      "source": "OCR",
      "page": 7
    }
  },
  {
    "text": "important contemporary performing arts events in the world. The festival features theater,",
    "features": {
      "source": "OCR",
      "page": 7
    }
  },
  {
    "text": "dance, and music performances in various historic venues throughout the city. Avignon's",
    "features": {
      "source": "OCR",
      "page": 7
    }
  },
  {
    "text": "cuisine is also notable, with local specialties such as truffles, olive oil, and wines from the",
    "features": {
      "source": "OCR",
      "page": 7
    }
  },
  {
    "text": "surrounding vineyards.",
    "features": {
      "source": "OCR",
      "page": 7
    }
  },
  {
    "text": "Aix-en-Provence: A City of Art and Culture",
    "features": {
      "source": "OCR",
      "page": 8
    }
  },
  {
    "text": "History",
    "features": {
      "source": "OCR",
      "page": 8
    }
  },
  {
    "text": "Aix-en-Provence, founded by the Romans in 123 BC, is known for its elegant architecture,",
    "features": {
      "source": "OCR",
      "page": 8
    }
  },
  {
    "text": "vibrant cultural scene, and association with the painter Paul C\u00e9zanne. The city's rich history is",
    "features": {
      "source": "OCR",
      "page": 8
    }
  },
  {
    "text": "reflected in its beautiful buildings and lively atmosphere. Aix-en-Provence has been a center",
    "features": {
      "source": "OCR",
      "page": 8
    }
  },
  {
    "text": "of art and learning for centuries, attracting artists, writers, and scholars.",
    "features": {
      "source": "OCR",
      "page": 8
    }
  },
  {
    "text": "Key Attractions",
    "features": {
      "source": "OCR",
      "page": 8
    }
  },
  {
    "text": "\u00ab Cours Mirabeau: This grand boulevard, lined with plane trees, cafes, and fountains, is",
    "features": {
      "source": "OCR",
      "page": 8
    }
  },
  {
    "text": "the heart of Aix-en-Provence. It is a great place to soak up the city's atmosphere.",
    "features": {
      "source": "OCR",
      "page": 8
    }
  },
  {
    "text": "\u00ab Saint-Sauveur Cathedral: This cathedral, built between the 5th and 17th centuries,",
    "features": {
      "source": "OCR",
      "page": 8
    }
  },
  {
    "text": "features a mix of architectural styles, including Romanesque, Gothic, and Baroque. It is",
    "features": {
      "source": "OCR",
      "page": 8
    }
  },
  {
    "text": "known for its beautiful cloister and triptych by Nicolas Froment.",
    "features": {
      "source": "OCR",
      "page": 8
    }
  },
  {
    "text": "+ Hotel de Ville: The town hall of Aix-en-Provence, built in the 17th century, is an elegant",
    "features": {
      "source": "OCR",
      "page": 8
    }
  },
  {
    "text": "building with a beautiful clock tower and an ornate facade. The square in front of the",
    "features": {
      "source": "OCR",
      "page": 8
    }
  },
  {
    "text": "Hotel de Ville is a lively spot, often hosting markets and events.",
    "features": {
      "source": "OCR",
      "page": 8
    }
  },
  {
    "text": "e Atelier C\u00e9zanne: The studio of Paul C\u00e9zanne, one of the most famous painters",
    "features": {
      "source": "OCR",
      "page": 8
    }
  },
  {
    "text": "associated with Aix-en-Provence, is preserved as a museum. Visitors can see where",
    "features": {
      "source": "OCR",
      "page": 8
    }
  },
  {
    "text": "C\u00e9zanne created many of his masterpieces and gain insight into his artistic process.",
    "features": {
      "source": "OCR",
      "page": 8
    }
  },
  {
    "text": "Artistic Heritage",
    "features": {
      "source": "OCR",
      "page": 8
    }
  },
  {
    "text": "+ Walking Tour: Take a walking tour of sites related to Paul C\u00e9zanne, such as the Terrain",
    "features": {
      "source": "OCR",
      "page": 8
    }
  },
  {
    "text": "des Peintres and the Bib\u00e9mus Quarry.",
    "features": {
      "source": "OCR",
      "page": 8
    }
  },
  {
    "text": "e Local Markets: Visit the city's famous markets, such as the flower market at Place de",
    "features": {
      "source": "OCR",
      "page": 8
    }
  },
  {
    "text": "l'H\u00e9tel de Ville or the food market at Place Richelme.",
    "features": {
      "source": "OCR",
      "page": 8
    }
  },
  {
    "text": "Cultural Highlights",
    "features": {
      "source": "OCR",
      "page": 8
    }
  },
  {
    "text": "Aix-en-Provence is known for its vibrant arts scene, with numerous galleries, theaters, and",
    "features": {
      "source": "OCR",
      "page": 8
    }
  },
  {
    "text": "music venues. The city hosts several festivals throughout the year, including the Festival d'Aix-",
    "features": {
      "source": "OCR",
      "page": 8
    }
  },
  {
    "text": "en-Provence, which features opera and classical music performances. Aix-en-Provence's",
    "features": {
      "source": "OCR",
      "page": 8
    }
  },
  {
    "text": "cuisine is also a highlight, with local specialties such as calissons (almond-shaped candies)",
    "features": {
      "source": "OCR",
      "page": 8
    }
  },
  {
    "text": "and Provencal dishes made with fresh, local ingredients.",
    "features": {
      "source": "OCR",
      "page": 8
    }
  },
  {
    "text": "Toulouse: The Pink City",
    "features": {
      "source": "OCR",
      "page": 9
    }
  },
  {
    "text": "History",
    "features": {
      "source": "OCR",
      "page": 9
    }
  },
  {
    "text": "Toulouse, known as \"La Ville Rose\" (The Pink City) due to its distinctive terracotta buildings,",
    "features": {
      "source": "OCR",
      "page": 9
    }
  },
  {
    "text": "is a vibrant city with a rich history. It was an important center during the Roman period and",
    "features": {
      "source": "OCR",
      "page": 9
    }
  },
  {
    "text": "later became a hub of the aerospace industry. Toulouse has been a center of learning and",
    "features": {
      "source": "OCR",
      "page": 9
    }
  },
  {
    "text": "culture for centuries, with a prestigious university and numerous research institutions.",
    "features": {
      "source": "OCR",
      "page": 9
    }
  },
  {
    "text": "Key Attractions",
    "features": {
      "source": "OCR",
      "page": 9
    }
  },
  {
    "text": "Basilica of Saint-Sernin: This Romanesque basilica, built between the 11th and 13th",
    "features": {
      "source": "OCR",
      "page": 9
    }
  },
  {
    "text": "centuries, isa UNESCO World Heritage site. It is one of the largest and best-preserved",
    "features": {
      "source": "OCR",
      "page": 9
    }
  },
  {
    "text": "Romanesque churches in Europe.",
    "features": {
      "source": "OCR",
      "page": 9
    }
  },
  {
    "text": "Capitole de Toulouse: The city\u2019s town hall and theater, the Capitole, is an impressive",
    "features": {
      "source": "OCR",
      "page": 9
    }
  },
  {
    "text": "building with a neoclassical facade. It has been the seat of municipal power since the",
    "features": {
      "source": "OCR",
      "page": 9
    }
  },
  {
    "text": "12th century.",
    "features": {
      "source": "OCR",
      "page": 9
    }
  },
  {
    "text": "Jacobins Convent: This Gothic convent, founded in the 13th century, is known for its",
    "features": {
      "source": "OCR",
      "page": 9
    }
  },
  {
    "text": "beautiful cloister and the relics of Saint Thomas Aquinas.",
    "features": {
      "source": "OCR",
      "page": 9
    }
  },
  {
    "text": "Cit\u00e9 de l'Espace: This space-themed science museum features interactive exhibits, a",
    "features": {
      "source": "OCR",
      "page": 9
    }
  },
  {
    "text": "planetarium, and a replica of the Mir space station. It's an engaging and educational",
    "features": {
      "source": "OCR",
      "page": 9
    }
  },
  {
    "text": "experience for visitors of all ages.",
    "features": {
      "source": "OCR",
      "page": 9
    }
  },
  {
    "text": "Aerospace Industry",
    "features": {
      "source": "OCR",
      "page": 9
    }
  },
  {
    "text": "Airbus Factory Tours: Visit the Airbus factory for a fascinating tour of one of the",
    "features": {
      "source": "OCR",
      "page": 9
    }
  },
  {
    "text": "world's leading aircraft manufacturers.",
    "features": {
      "source": "OCR",
      "page": 9
    }
  },
  {
    "text": "Aeroscopia Museum: Explore the history of aviation at the Aeroscopia Museum, which",
    "features": {
      "source": "OCR",
      "page": 9
    }
  },
  {
    "text": "features a collection of historic aircraft.",
    "features": {
      "source": "OCR",
      "page": 9
    }
  },
  {
    "text": "Cultural Highlights",
    "features": {
      "source": "OCR",
      "page": 9
    }
  },
  {
    "text": "Toulouse is renowned for its vibrant cultural scene, with numerous theaters, music venues,",
    "features": {
      "source": "OCR",
      "page": 9
    }
  },
  {
    "text": "and festivals. The city hosts the Toulouse International Art Festival, which features",
    "features": {
      "source": "OCR",
      "page": 9
    }
  },
  {
    "text": "contemporary art exhibitions and performances. Toulouse's cuisine is also notable, with local",
    "features": {
      "source": "OCR",
      "page": 9
    }
  },
  {
    "text": "specialties such as cassoulet (a hearty bean and meat stew) and foie gras being popular",
    "features": {
      "source": "OCR",
      "page": 9
    }
  },
  {
    "text": "dishes.",
    "features": {
      "source": "OCR",
      "page": 9
    }
  },
  {
    "text": "Montpellier: A University City with Medieval Charm",
    "features": {
      "source": "OCR",
      "page": 10
    }
  },
  {
    "text": "History",
    "features": {
      "source": "OCR",
      "page": 10
    }
  },
  {
    "text": "Montpellier, founded in the 10th century, is known for its prestigious university and vibrant",
    "features": {
      "source": "OCR",
      "page": 10
    }
  },
  {
    "text": "cultural scene. The city has a rich history, with a blend of medieval, Renaissance, and modern",
    "features": {
      "source": "OCR",
      "page": 10
    }
  },
  {
    "text": "architecture. Montpellier has been a center of learning and innovation for centuries, attracting",
    "features": {
      "source": "OCR",
      "page": 10
    }
  },
  {
    "text": "scholars and students from around the world.",
    "features": {
      "source": "OCR",
      "page": 10
    }
  },
  {
    "text": "Key Attractions",
    "features": {
      "source": "OCR",
      "page": 10
    }
  },
  {
    "text": "\u00ab Place de la Com\u00e9die: The central square of Montpellier, this bustling area is",
    "features": {
      "source": "OCR",
      "page": 10
    }
  },
  {
    "text": "surrounded by cafes, shops, and the impressive Op\u00e9ra Com\u00e9die. It is a great place to",
    "features": {
      "source": "OCR",
      "page": 10
    }
  },
  {
    "text": "start exploring the city.",
    "features": {
      "source": "OCR",
      "page": 10
    }
  },
  {
    "text": "e Saint-Pierre Cathedral: This Gothic cathedral, built in the 14th century, is known for its",
    "features": {
      "source": "OCR",
      "page": 10
    }
  },
  {
    "text": "imposing facade and twin towers. It is the seat of the Archdiocese of Montpellier.",
    "features": {
      "source": "OCR",
      "page": 10
    }
  },
  {
    "text": "\u00ab Promenade du Peyrou: This 17th-century promenade offers stunning views of the city",
    "features": {
      "source": "OCR",
      "page": 10
    }
  },
  {
    "text": "and features the Arc de Triomphe and the Chateau d'Eau, a beautiful water tower.",
    "features": {
      "source": "OCR",
      "page": 10
    }
  },
  {
    "text": "e Mus\u00e9e Fabre: One of the most important art museums in France, the Mus\u00e9e Fabre",
    "features": {
      "source": "OCR",
      "page": 10
    }
  },
  {
    "text": "houses an extensive collection of European paintings, sculptures, and decorative arts.",
    "features": {
      "source": "OCR",
      "page": 10
    }
  },
  {
    "text": "Student Life",
    "features": {
      "source": "OCR",
      "page": 10
    }
  },
  {
    "text": "e University Influence: Highlight the vibrant student life and the influence of the",
    "features": {
      "source": "OCR",
      "page": 10
    }
  },
  {
    "text": "university on the city's culture.",
    "features": {
      "source": "OCR",
      "page": 10
    }
  },
  {
    "text": "e Modern Architecture: Mention modern architectural landmarks like the Antigone",
    "features": {
      "source": "OCR",
      "page": 10
    }
  },
  {
    "text": "district or the Pierresvives building.",
    "features": {
      "source": "OCR",
      "page": 10
    }
  },
  {
    "text": "Cultural Highlights",
    "features": {
      "source": "OCR",
      "page": 10
    }
  },
  {
    "text": "Montpellier is renowned for its vibrant cultural scene, with numerous theaters, music venues,",
    "features": {
      "source": "OCR",
      "page": 10
    }
  },
  {
    "text": "and festivals. The city hosts the Montpellier Dance Festival, which attracts contemporary",
    "features": {
      "source": "OCR",
      "page": 10
    }
  },
  {
    "text": "dance companies from around the world. Montpellier's cuisine is also notable, with local",
    "features": {
      "source": "OCR",
      "page": 10
    }
  },
  {
    "text": "specialties such as tielle (a savory pie filled with octopus) and wines from the surrounding",
    "features": {
      "source": "OCR",
      "page": 10
    }
  },
  {
    "text": "vineyards.",
    "features": {
      "source": "OCR",
      "page": 10
    }
  },
  {
    "text": "Perpignan: A Blend of French and Catalan Cultures",
    "features": {
      "source": "OCR",
      "page": 11
    }
  },
  {
    "text": "History",
    "features": {
      "source": "OCR",
      "page": 11
    }
  },
  {
    "text": "Perpignan, located near the Spanish border, has a unique blend of French and Catalan",
    "features": {
      "source": "OCR",
      "page": 11
    }
  },
  {
    "text": "influences. The city was once the capital of the Kingdom of Majorca and has a rich history",
    "features": {
      "source": "OCR",
      "page": 11
    }
  },
  {
    "text": "reflected in its architecture and culture. Perpignan\u2019s strategic location has made it a",
    "features": {
      "source": "OCR",
      "page": 11
    }
  },
  {
    "text": "crossroads of cultures and traditions.",
    "features": {
      "source": "OCR",
      "page": 11
    }
  },
  {
    "text": "Key Attractions",
    "features": {
      "source": "OCR",
      "page": 11
    }
  },
  {
    "text": "\u00ab Palace of the Kings of Majorca: This impressive fortress, built in the 13th century, was",
    "features": {
      "source": "OCR",
      "page": 11
    }
  },
  {
    "text": "the residence of the Kings of Majorca. It offers panoramic views of the city and the",
    "features": {
      "source": "OCR",
      "page": 11
    }
  },
  {
    "text": "surrounding countryside.",
    "features": {
      "source": "OCR",
      "page": 11
    }
  },
  {
    "text": "\u00a2 Perpignan Cathedral: Also known as the Cathedral of Saint John the Baptist, this",
    "features": {
      "source": "OCR",
      "page": 11
    }
  },
  {
    "text": "Gothic cathedral was built in the 14th century and features a beautiful cloister and bell",
    "features": {
      "source": "OCR",
      "page": 11
    }
  },
  {
    "text": "tower.",
    "features": {
      "source": "OCR",
      "page": 11
    }
  },
  {
    "text": "\u00ab Castillet: This iconic red-brick gatehouse, built in the 14th century, is a symbol of",
    "features": {
      "source": "OCR",
      "page": 11
    }
  },
  {
    "text": "Perpignan. It now houses the Casa Pairal Museum, which showcases the history and",
    "features": {
      "source": "OCR",
      "page": 11
    }
  },
  {
    "text": "culture of the region.",
    "features": {
      "source": "OCR",
      "page": 11
    }
  },
  {
    "text": "\u00ab Loge de Mer: This historic building, originally a maritime trading exchange, dates back",
    "features": {
      "source": "OCR",
      "page": 11
    }
  },
  {
    "text": "to the 14th century. It is located in the heart of the old town and is a testament to",
    "features": {
      "source": "OCR",
      "page": 11
    }
  },
  {
    "text": "Perpignan's rich mercantile history.",
    "features": {
      "source": "OCR",
      "page": 11
    }
  },
  {
    "text": "Cultural Fusion",
    "features": {
      "source": "OCR",
      "page": 11
    }
  },
  {
    "text": "e Festivals: Emphasize the blend of French and Catalan cultures in the city's festivals,",
    "features": {
      "source": "OCR",
      "page": 11
    }
  },
  {
    "text": "cuisine, and traditions.",
    "features": {
      "source": "OCR",
      "page": 11
    }
  },
  {
    "text": "e Beaches and Nature: Suggest visiting nearby beaches like Canet-en-Roussillon or",
    "features": {
      "source": "OCR",
      "page": 11
    }
  },
  {
    "text": "exploring the Pyrenees mountains.",
    "features": {
      "source": "OCR",
      "page": 11
    }
  },
  {
    "text": "Cultural Highlights",
    "features": {
      "source": "OCR",
      "page": 11
    }
  },
  {
    "text": "Perpignan is known for its vibrant cultural scene, with a strong emphasis on Catalan",
    "features": {
      "source": "OCR",
      "page": 11
    }
  },
  {
    "text": "traditions. The city hosts the Guitares au Palais festival, which celebrates guitar music in",
    "features": {
      "source": "OCR",
      "page": 11
    }
  },
  {
    "text": "various genres. Perpignan's cuisine is also notable, with local specialties such as cargolade",
    "features": {
      "source": "OCR",
      "page": 11
    }
  },
  {
    "text": "(grilled snails) and wines from the Roussillon region.",
    "features": {
      "source": "OCR",
      "page": 11
    }
  },
  {
    "text": "Arles: A Roman Treasure",
    "features": {
      "source": "OCR",
      "page": 12
    }
  },
  {
    "text": "History",
    "features": {
      "source": "OCR",
      "page": 12
    }
  },
  {
    "text": "Arles, located on the banks of the Rh\u00e9ne River, is renowned for its Roman and Romanesque",
    "features": {
      "source": "OCR",
      "page": 12
    }
  },
  {
    "text": "monuments. The city was an important Roman settlement and later became a center of",
    "features": {
      "source": "OCR",
      "page": 12
    }
  },
  {
    "text": "Christian pilgrimage. Arles has a rich artistic heritage, having inspired artists such as Vincent",
    "features": {
      "source": "OCR",
      "page": 12
    }
  },
  {
    "text": "van Gogh and Pablo Picasso.",
    "features": {
      "source": "OCR",
      "page": 12
    }
  },
  {
    "text": "Key Attractions",
    "features": {
      "source": "OCR",
      "page": 12
    }
  },
  {
    "text": "e Arles Amphitheatre: This Roman amphitheater, built in the Ist century AD, is still used",
    "features": {
      "source": "OCR",
      "page": 12
    }
  },
  {
    "text": "for events such as bullfights and concerts. It is one of the best-preserved Roman",
    "features": {
      "source": "OCR",
      "page": 12
    }
  },
  {
    "text": "structures in France.",
    "features": {
      "source": "OCR",
      "page": 12
    }
  },
  {
    "text": "e Church of St. Trophime: This Romanesque church, built in the 12th century, is known",
    "features": {
      "source": "OCR",
      "page": 12
    }
  },
  {
    "text": "for its stunning portal and cloister. It was an important stop on the pilgrimage route to",
    "features": {
      "source": "OCR",
      "page": 12
    }
  },
  {
    "text": "Santiago de Compostela.",
    "features": {
      "source": "OCR",
      "page": 12
    }
  },
  {
    "text": "\u00ab Alyscamps: This ancient Roman necropolis, located just outside the city walls, was a",
    "features": {
      "source": "OCR",
      "page": 12
    }
  },
  {
    "text": "major burial site in antiquity. It features a long avenue lined with sarcophagi.",
    "features": {
      "source": "OCR",
      "page": 12
    }
  },
  {
    "text": "\u00a2 Thermes de Constantin: These Roman baths, built in the 4th century AD, are a",
    "features": {
      "source": "OCR",
      "page": 12
    }
  },
  {
    "text": "testament to the city's importance during the Roman period.",
    "features": {
      "source": "OCR",
      "page": 12
    }
  },
  {
    "text": "Artistic Influence",
    "features": {
      "source": "OCR",
      "page": 12
    }
  },
  {
    "text": "e Vincent van Gogh: Include a section on Vincent van Gogh's time in Arles and the",
    "features": {
      "source": "OCR",
      "page": 12
    }
  },
  {
    "text": "locations that inspired his paintings.",
    "features": {
      "source": "OCR",
      "page": 12
    }
  },
  {
    "text": "\u00a2 Photography: Recommend visiting during the Rencontres d'Arles photography festival",
    "features": {
      "source": "OCR",
      "page": 12
    }
  },
  {
    "text": "for a unique cultural experience.",
    "features": {
      "source": "OCR",
      "page": 12
    }
  },
  {
    "text": "Cultural Highlights",
    "features": {
      "source": "OCR",
      "page": 12
    }
  },
  {
    "text": "Arles is known for its vibrant arts scene, with numerous galleries, theaters, and festivals. The",
    "features": {
      "source": "OCR",
      "page": 12
    }
  },
  {
    "text": "city hosts the Rencontres d\u2019Arles, an international photography festival that attracts artists",
    "features": {
      "source": "OCR",
      "page": 12
    }
  },
  {
    "text": "and photographers from around the world. Arles\u2019 cuisine is also notable, with local specialties",
    "features": {
      "source": "OCR",
      "page": 12
    }
  },
  {
    "text": "such as bull meat stew and wines from the surrounding vineyards.",
    "features": {
      "source": "OCR",
      "page": 12
    }
  },
  {
    "text": "Carcassonne: A Medieval Fortress",
    "features": {
      "source": "OCR",
      "page": 13
    }
  },
  {
    "text": "History",
    "features": {
      "source": "OCR",
      "page": 13
    }
  },
  {
    "text": "Carcassonne is a fortified city in the Languedoc region, known for its well-preserved medieval",
    "features": {
      "source": "OCR",
      "page": 13
    }
  },
  {
    "text": "architecture. The city's history dates back to the Roman period, but it is best known for its",
    "features": {
      "source": "OCR",
      "page": 13
    }
  },
  {
    "text": "role in the medieval period as a stronghold during the Albigensian Crusade. Carcassonne's",
    "features": {
      "source": "OCR",
      "page": 13
    }
  },
  {
    "text": "double-walled fortifications and 52 towers make it one of the most impressive examples of",
    "features": {
      "source": "OCR",
      "page": 13
    }
  },
  {
    "text": "medieval architecture in Europe.",
    "features": {
      "source": "OCR",
      "page": 13
    }
  },
  {
    "text": "Key Attractions",
    "features": {
      "source": "OCR",
      "page": 13
    }
  },
  {
    "text": "\u00bb Cit\u00e9 de Carcassonne: This medieval fortress is a UNESCO World Heritage site and one",
    "features": {
      "source": "OCR",
      "page": 13
    }
  },
  {
    "text": "of the most impressive examples of medieval architecture in Europe. It features double",
    "features": {
      "source": "OCR",
      "page": 13
    }
  },
  {
    "text": "walls, 52 towers, and a castle.",
    "features": {
      "source": "OCR",
      "page": 13
    }
  },
  {
    "text": "* Basilica of Saints Nazarius and Celsus: This Gothic-Romanesque basilica, located",
    "features": {
      "source": "OCR",
      "page": 13
    }
  },
  {
    "text": "within the fortress, dates back to the Ith century. It is known for its beautiful stained",
    "features": {
      "source": "OCR",
      "page": 13
    }
  },
  {
    "text": "glass windows.",
    "features": {
      "source": "OCR",
      "page": 13
    }
  },
  {
    "text": "\u00bb Chateau Comtal: This castle, located within the Cit\u00e9, offers guided tours that provide",
    "features": {
      "source": "OCR",
      "page": 13
    }
  },
  {
    "text": "insight into the history and architecture of Carcassonne.",
    "features": {
      "source": "OCR",
      "page": 13
    }
  },
  {
    "text": "\u00ab Pont Vieux: This 14th-century bridge connects the medieval Cit\u00e9 with the lower town.",
    "features": {
      "source": "OCR",
      "page": 13
    }
  },
  {
    "text": "It offers stunning views of the fortress and the surrounding countryside.",
    "features": {
      "source": "OCR",
      "page": 13
    }
  },
  {
    "text": "Medieval Life",
    "features": {
      "source": "OCR",
      "page": 13
    }
  },
  {
    "text": "\u00ab Reenactments: Provide insights into medieval life in Carcassonne, including",
    "features": {
      "source": "OCR",
      "page": 13
    }
  },
  {
    "text": "reenactments and historical tours.",
    "features": {
      "source": "OCR",
      "page": 13
    }
  },
  {
    "text": "e Surrounding Area: Suggest exploring the surrounding Languedoc region, known for its",
    "features": {
      "source": "OCR",
      "page": 13
    }
  },
  {
    "text": "vineyards and picturesque villages.",
    "features": {
      "source": "OCR",
      "page": 13
    }
  },
  {
    "text": "Cultural Highlights",
    "features": {
      "source": "OCR",
      "page": 13
    }
  },
  {
    "text": "Carcassonne is known for its vibrant cultural scene, with numerous festivals and events",
    "features": {
      "source": "OCR",
      "page": 13
    }
  },
  {
    "text": "throughout the year. The city hosts the Festival de Carcassonne, which features music,",
    "features": {
      "source": "OCR",
      "page": 13
    }
  },
  {
    "text": "theater, and dance performances in various historic venues. Carcassonne's cuisine is also",
    "features": {
      "source": "OCR",
      "page": 13
    }
  },
  {
    "text": "notable, with local specialties such as cassoulet (a hearty bean and meat stew) and wines",
    "features": {
      "source": "OCR",
      "page": 13
    }
  },
  {
    "text": "from the surrounding vineyards.",
    "features": {
      "source": "OCR",
      "page": 13
    }
  },
  {
    "text": "Conclusion",
    "features": {
      "source": "OCR",
      "page": 14
    }
  },
  {
    "text": "The South of France is home to a diverse array of cities, each with its own unique history,",
    "features": {
      "source": "OCR",
      "page": 14
    }
  },
  {
    "text": "culture, and attractions. From the ancient Reman ruins of Arles and Nimes to the medieval",
    "features": {
      "source": "OCR",
      "page": 14
    }
  },
  {
    "text": "fortresses of Carcassonne and Avignon, each city offers a glimpse into the rich heritage of the",
    "features": {
      "source": "OCR",
      "page": 14
    }
  },
  {
    "text": "region. Whether you're exploring the vibrant streets of Marseille, the elegant boulevards of",
    "features": {
      "source": "OCR",
      "page": 14
    }
  },
  {
    "text": "Aix-en-Provence, or the charming squares of Montpellier, you'll find a wealth of historical",
    "features": {
      "source": "OCR",
      "page": 14
    }
  },
  {
    "text": "treasures and cultural experiences waiting to be discovered. Use this guide to plan your",
    "features": {
      "source": "OCR",
      "page": 14
    }
  },
  {
    "text": "journey through the South of France and immerse yourself in the fascinating history and",
    "features": {
      "source": "OCR",
      "page": 14
    }
  },
  {
    "text": "culture of this beautiful region.",
    "features": {
      "source": "OCR",
      "page": 14
    }
  }
]